sopel_modules.twitter-0.4.0-nspkg.pth
sopel_modules/twitter/__init__.py
sopel_modules/twitter/twitter.py
tests/__init__.py
tests/test_twitter.py
sopel_modules.twitter-0.4.0.dist-info/COPYING
sopel_modules.twitter-0.4.0.dist-info/METADATA
sopel_modules.twitter-0.4.0.dist-info/WHEEL
sopel_modules.twitter-0.4.0.dist-info/namespace_packages.txt
sopel_modules.twitter-0.4.0.dist-info/top_level.txt
sopel_modules.twitter-0.4.0.dist-info/RECORD
