Metadata-Version: 2.1
Name: sopel-modules.twitter
Version: 0.4.0
Summary: A Twitter plugin for Sopel
Home-page: https://github.com/sopel-irc/sopel-twitter
Author: dgw
Author-email: dgw@technobabbl.es
License: Eiffel Forum License, version 2
Platform: UNKNOWN
Requires-Dist: oauth2 (<2.0)
Requires-Dist: sopel (<8,>=7)
